{"crab":{"width":16,"height":16,"show":true},"hermitcrab":{"width":16,"height":16,"show":true},"lionfish":{"width":16,"height":16,"show":true},"opah":{"width":16,"height":16,"show":true},"yellowfin":{"width":16,"height":16,"show":true},"clownfish":{"width":16,"height":16,"show":true},"cuttlefish":{"width":16,"height":16,"show":true},"jellyfish":{"width":16,"height":16,"show":true},"sunfish":{"width":16,"height":16,"show":true},"whaleshark":{"width":16,"height":16,"show":true},"seahorse":{"width":16,"height":16,"show":true},"moonjelly":{"width":16,"height":16,"show":true},"spottedstingray":{"width":16,"height":16,"show":true},"shark":{"width":16,"height":16,"show":true},"piranha":{"width":16,"height":16,"show":true},"betta":{"width":16,"height":16,"show":true}}